{
  "id": 48,
  "targetCommon": {
    "startMoney": 800,
    "targetMoney": 5000,
    "timeMission": 27,
    "maxCustomer": 45,
    "targetCustomerRate": 350,
    "itemsInShop": [],
    "startScene": 1
  },
  "starCondition": {
    "twoStar": 5000,
    "threeStar": 6800,
    "reward": [
      1,
      1,
      2
    ]
  },
  "farmData": {
    "isCanSick": false,
    "fields": [
      {
        "idField": 1,
        "startNumber": 9,
        "targetNumber": 0,
        "startLevel": 2,
        "targetLevel": 1,
        "maxLevel": 2
      },
      {
        "idField": 2,
        "startNumber": 5,
        "targetNumber": 0,
        "startLevel": 1,
        "targetLevel": 1,
        "maxLevel": 2
      },
      {
        "idField": 3,
        "startNumber": 3,
        "targetNumber": 0,
        "startLevel": 1,
        "targetLevel": 1,
        "maxLevel": 2
      }
    ],
    "breeds": [
      {
        "idBreed": 1,
        "startNumber": 0,
        "targetNumber": 0
      },
      {
        "idBreed": 3,
        "startNumber": 0,
        "targetNumber": 0
      },
      {
        "idBreed": 4,
        "startNumber": 0,
        "targetNumber": 0
      },
      {
        "idBreed": 5,
        "startNumber": 0,
        "targetNumber": 0
      },
      {
        "idBreed": 7,
        "startNumber": 0,
        "targetNumber": 0
      },
      {
        "idBreed": 8,
        "startNumber": 0,
        "targetNumber": 0
      }
    ],
    "harvestField": {
      "idField": 1,
      "targetNumber": 0
    },
    "harvestCage": {
      "idField": 2,
      "targetNumber": 0
    }
  },
  "tip_vi": "",
  "tip_en": ""
}